pycellino/__init__.py
pycellino/functions.py
pycellino/decorators/__init__.py
pycellino/decorators/main.py
pycellino/decorators/test_decorators.py
pycellino/imputation/__init__.py
pycellino/imputation/main.py
pycellino/imputation/test_imputation.py
pycellino/normalization/main.py
pycellino/tests/__init__.py
pycellino/tests/test_functions.py
pycellino-0.2.1.dist-info/LICENSE
pycellino-0.2.1.dist-info/METADATA
pycellino-0.2.1.dist-info/WHEEL
pycellino-0.2.1.dist-info/top_level.txt
pycellino-0.2.1.dist-info/RECORD
